pluginbase.py
pluginbase-0.3.dist-info/DESCRIPTION.rst
pluginbase-0.3.dist-info/METADATA
pluginbase-0.3.dist-info/metadata.json
pluginbase-0.3.dist-info/RECORD
pluginbase-0.3.dist-info/top_level.txt
pluginbase-0.3.dist-info/WHEEL
