Metadata-Version: 2.0
Name: pluginbase
Version: 0.3
Summary: A support library for building plugins sytems in Python.
Home-page: http://github.com/mitsuhiko/pluginbase
Author: Armin Ronacher
Author-email: armin.ronacher@active-4.com
License: UNKNOWN
Platform: UNKNOWN
Classifier: License :: OSI Approved :: BSD License
Classifier: Programming Language :: Python
Classifier: Programming Language :: Python :: 3
